[{"line":2,"elements":[{"start_timestamp":"2025-04-22T14:31:51.684Z","before":[{"result":{"duration":2392311400,"status":"passed"},"match":{"location":"e2e.test.saucedemo.utils.Setup.setWebDriver(io.cucumber.java.Scenario)"}}],"line":36,"name":"Add many products in cart","description":"","id":"en-tant-que-utilisateur-je-veux-ajouter-des-produits-dans-la-carte;add-many-products-in-cart;;2","type":"scenario","keyword":"Scenario Outline","steps":[{"result":{"duration":569518600,"status":"passed"},"line":27,"name":"utilisateur ouvre l application","match":{"location":"e2e.test.saucedemo.stepdefinitions.LoginStepDefinitions.utilisateurOuvreLApplication()"},"keyword":"Given "},{"result":{"duration":164313600,"status":"passed"},"line":28,"name":"saisir username valide","match":{"location":"e2e.test.saucedemo.stepdefinitions.LoginStepDefinitions.saisirUsernameValide()"},"keyword":"When "},{"result":{"duration":120163500,"status":"passed"},"line":29,"name":"saisir mdp valide","match":{"location":"e2e.test.saucedemo.stepdefinitions.LoginStepDefinitions.saisirMdpValide()"},"keyword":"And "},{"result":{"duration":121220600,"status":"passed"},"line":30,"name":"cliquer sur le bouton Login","match":{"location":"e2e.test.saucedemo.stepdefinitions.LoginStepDefinitions.cliquerSurLeBoutonLogin()"},"keyword":"And "},{"result":{"duration":254664400,"status":"passed"},"line":31,"name":"ajouter des produits \"Sauce Labs Onesie, Sauce Labs Backpack\"","match":{"arguments":[{"val":"\"Sauce Labs Onesie, Sauce Labs Backpack\"","offset":21}],"location":"e2e.test.saucedemo.stepdefinitions.AddProductInCartStepDefinitions.ajouterDesProduits(java.lang.String)"},"keyword":"When "},{"result":{"duration":56894400,"status":"passed"},"line":32,"name":"cliquer sur le bouton panier","match":{"location":"e2e.test.saucedemo.stepdefinitions.AddProductInCartStepDefinitions.cliquerSurLeBoutonPanier()"},"keyword":"When "},{"result":{"duration":38853500,"status":"passed"},"line":33,"name":"verifier les produits correspondants affiches","match":{"location":"e2e.test.saucedemo.stepdefinitions.AddProductInCartStepDefinitions.verifierLesProduitsCorrespondantsAffiches()"},"keyword":"Then "}],"tags":[{"name":"@AddProductInCart"},{"name":"@AddManyProducts"}]}],"name":"En tant que utilisateur je veux ajouter des produits dans la carte","description":"","id":"en-tant-que-utilisateur-je-veux-ajouter-des-produits-dans-la-carte","keyword":"Feature","uri":"file:src/spec/features/AddProductInCart.feature","tags":[{"name":"@AddProductInCart","type":"Tag","location":{"line":1,"column":1}}]}]